ms_image_process/__init__.py
ms_image_process/cli.py
ms_image_process-0.5.0.dist-info/licenses/LICENSE
ms_image_process-0.5.0.dist-info/METADATA
ms_image_process-0.5.0.dist-info/WHEEL
ms_image_process-0.5.0.dist-info/entry_points.txt
ms_image_process-0.5.0.dist-info/top_level.txt
ms_image_process-0.5.0.dist-info/RECORD
