Metadata-Version: 2.4
Name: ms-image-process
Version: 0.5.0
Summary: A simple CLI tool for processing images.
Author-email: Mohammad Sarabi <dev@m-sarabi.ir>
License-Expression: MIT
Project-URL: Homepage, https://github.com/m-sarabi/ms-image-process
Project-URL: Documentation, https://github.com/m-sarabi/ms-image-process/blob/main/README.md
Project-URL: Repository, https://github.com/m-sarabi/ms-image-process
Project-URL: Issues, https://github.com/m-sarabi/ms-image-process/issues
Classifier: Development Status :: 4 - Beta
Classifier: Environment :: Console
Classifier: Intended Audience :: Developers
Classifier: Natural Language :: English
Classifier: Operating System :: OS Independent
Classifier: Programming Language :: Python :: 3
Classifier: Programming Language :: Python :: 3.8
Classifier: Programming Language :: Python :: 3.9
Classifier: Programming Language :: Python :: 3.10
Classifier: Programming Language :: Python :: 3.11
Classifier: Programming Language :: Python :: 3.12
Classifier: Programming Language :: Python :: 3.13
Classifier: Topic :: Multimedia :: Graphics :: Editors :: Raster-Based
Classifier: Topic :: Multimedia :: Graphics :: Graphics Conversion
Classifier: Topic :: Scientific/Engineering :: Image Processing
Classifier: Topic :: Software Development :: Libraries :: Python Modules
Classifier: Topic :: Utilities
Requires-Python: >=3.8
License-File: LICENSE
Requires-Dist: pillow
Requires-Dist: click
Dynamic: license-file
